{"geocoding": {"version": "0.2", "attribution": "https://openrouteservice.org/terms-of-service/#attribution-geocode", "query": {"text": "SL6 4DT, UK", "size": 1, "private": false, "lang": {"name": "English", "iso6391": "en", "iso6393": "eng", "via": "default", "defaulted": true}, "querySize": 20, "parser": "libpostal", "parsed_text": {"postalcode": "sl6 4dt", "country": "uk"}}, "engine": {"name": "Pelias", "author": "Mapzen", "version": "1.0"}, "timestamp": 1780844714726}, "type": "FeatureCollection", "features": [{"type": "Feature", "geometry": {"type": "Point", "coordinates": [-0.73205, 51.517756]}, "properties": {"id": "471815365", "gid": "whosonfirst:postalcode:471815365", "layer": "postalcode", "source": "whosonfirst", "source_id": "471815365", "name": "SL6 4DT", "postalcode": "SL6 4DT", "postalcode_gid": "whosonfirst:postalcode:471815365", "confidence": 1, "match_type": "exact", "accuracy": "centroid", "country": "United Kingdom", "country_gid": "whosonfirst:country:85633159", "country_a": "GBR", "macroregion": "England", "macroregion_gid": "whosonfirst:macroregion:404227469", "region": "Berkshire", "region_gid": "whosonfirst:region:1360698529", "county": "Windsor and Maidenhead", "county_gid": "whosonfirst:county:1360698943", "locality": "Maidenhead", "locality_gid": "whosonfirst:locality:101750385", "continent": "Europe", "continent_gid": "whosonfirst:continent:102191581", "label": "SL6 4DT, Maidenhead, England, United Kingdom", "addendum": {"concordances": {"gp:id": "26545012"}}}, "bbox": [-0.73205, 51.517756, -0.73205, 51.517756]}], "bbox": [-0.73205, 51.517756, -0.73205, 51.517756]}